rdf_data_manager/__init__.py
rdf_data_manager-0.7.0.dist-info/METADATA
rdf_data_manager-0.7.0.dist-info/WHEEL
rdf_data_manager-0.7.0.dist-info/entry_points.txt
rdf_data_manager-0.7.0.dist-info/RECORD
